[{"corpusSize":7948,"step":1},{"corpusSize":4640,"step":2},{"corpusSize":4326,"step":3},{"corpusSize":4134,"step":4},{"corpusSize":3798,"step":5},{"corpusSize":3544,"step":6},{"corpusSize":3431,"step":7},{"corpusSize":3342,"step":8},{"corpusSize":3263,"step":9},{"corpusSize":3218,"step":10},{"corpusSize":3130,"step":11},{"corpusSize":3092,"step":12},{"corpusSize":3055,"step":13},{"corpusSize":3021,"step":14},{"corpusSize":2993,"step":15},{"corpusSize":2965,"step":16},{"corpusSize":2941,"step":17},{"corpusSize":2889,"step":18},{"corpusSize":2857,"step":19},{"corpusSize":2838,"step":20},{"corpusSize":2819,"step":21},{"corpusSize":2735,"step":22},{"corpusSize":2717,"step":23},{"corpusSize":2700,"step":24},{"corpusSize":2683,"step":25},{"corpusSize":2668,"step":26},{"corpusSize":2653,"step":27},{"corpusSize":2639,"step":28},{"corpusSize":2613,"step":29},{"corpusSize":2545,"step":30},{"corpusSize":2533,"step":31},{"corpusSize":2521,"step":32},{"corpusSize":2509,"step":33},{"corpusSize":2497,"step":34},{"corpusSize":2485,"step":35},{"corpusSize":2474,"step":36},{"corpusSize":2463,"step":37},{"corpusSize":2443,"step":38},{"corpusSize":2433,"step":39},{"corpusSize":2423,"step":40},{"corpusSize":2415,"step":41},{"corpusSize":2408,"step":42},{"corpusSize":2401,"step":43},{"corpusSize":2395,"step":44},{"corpusSize":2389,"step":45},{"corpusSize":2383,"step":46},{"corpusSize":2377,"step":47},{"corpusSize":2371,"step":48},{"corpusSize":2366,"step":49},{"corpusSize":2361,"step":50},{"corpusSize":2356,"step":51},{"corpusSize":2351,"step":52},{"corpusSize":2346,"step":53},{"corpusSize":2341,"step":54},{"corpusSize":2333,"step":55},{"corpusSize":2329,"step":56},{"corpusSize":2325,"step":57},{"corpusSize":2321,"step":58},{"corpusSize":2317,"step":59},{"corpusSize":2314,"step":60},{"corpusSize":2308,"step":61},{"corpusSize":2305,"step":62},{"corpusSize":2302,"step":63},{"corpusSize":2299,"step":64},{"corpusSize":2296,"step":65},{"corpusSize":2293,"step":66},{"corpusSize":2290,"step":67},{"corpusSize":2284,"step":68},{"corpusSize":2276,"step":69},{"corpusSize":2256,"step":70},{"corpusSize":2241,"step":71},{"corpusSize":2235,"step":72},{"corpusSize":2215,"step":73},{"corpusSize":2213,"step":74},{"corpusSize":2211,"step":75},{"corpusSize":2209,"step":76},{"corpusSize":2207,"step":77},{"corpusSize":2205,"step":78},{"corpusSize":2203,"step":79},{"corpusSize":2201,"step":80},{"corpusSize":2199,"step":81},{"corpusSize":2197,"step":82},{"corpusSize":2195,"step":83},{"corpusSize":2193,"step":84},{"corpusSize":2191,"step":85},{"corpusSize":2189,"step":86},{"corpusSize":2187,"step":87},{"corpusSize":2185,"step":88},{"corpusSize":2183,"step":89},{"corpusSize":2181,"step":90},{"corpusSize":2180,"step":91},{"corpusSize":2179,"step":92},{"corpusSize":2178,"step":93},{"corpusSize":2177,"step":94},{"corpusSize":2176,"step":95},{"corpusSize":2175,"step":96},{"corpusSize":2174,"step":97},{"corpusSize":2173,"step":98},{"corpusSize":2172,"step":99},{"corpusSize":2171,"step":100},{"corpusSize":2170,"step":101},{"corpusSize":2169,"step":102},{"corpusSize":2168,"step":103},{"corpusSize":2167,"step":104},{"corpusSize":2166,"step":105},{"corpusSize":2165,"step":106},{"corpusSize":2164,"step":107},{"corpusSize":2160,"step":108},{"corpusSize":2148,"step":109},{"corpusSize":2148,"step":110},{"corpusSize":2140,"step":111},{"corpusSize":2140,"step":112},{"corpusSize":2140,"step":113},{"corpusSize":2140,"step":114},{"corpusSize":2140,"step":115},{"corpusSize":2140,"step":116},{"corpusSize":2140,"step":117},{"corpusSize":2140,"step":118},{"corpusSize":2140,"step":119},{"corpusSize":2140,"step":120},{"corpusSize":2140,"step":121},{"corpusSize":2140,"step":122},{"corpusSize":2140,"step":123},{"corpusSize":2140,"step":124},{"corpusSize":2140,"step":125},{"corpusSize":2140,"step":126},{"corpusSize":2140,"step":127},{"corpusSize":2140,"step":128},{"corpusSize":2140,"step":129},{"corpusSize":2140,"step":130},{"corpusSize":2140,"step":131},{"corpusSize":2140,"step":132},{"corpusSize":2140,"step":133},{"corpusSize":2140,"step":134},{"corpusSize":2140,"step":135},{"corpusSize":2140,"step":136},{"corpusSize":2140,"step":137},{"corpusSize":2140,"step":138},{"corpusSize":2140,"step":139},{"corpusSize":2140,"step":140},{"corpusSize":2140,"step":141},{"corpusSize":2140,"step":142},{"corpusSize":2140,"step":143},{"corpusSize":2140,"step":144},{"corpusSize":2140,"step":145},{"corpusSize":2140,"step":146},{"corpusSize":2140,"step":147},{"corpusSize":2140,"step":148},{"corpusSize":2140,"step":149},{"corpusSize":2140,"step":150},{"corpusSize":2140,"step":151},{"corpusSize":2140,"step":152},{"corpusSize":2141,"step":153},{"corpusSize":2142,"step":154},{"corpusSize":2143,"step":155},{"corpusSize":2144,"step":156},{"corpusSize":2136,"step":157},{"corpusSize":2137,"step":158},{"corpusSize":2129,"step":159},{"corpusSize":2130,"step":160},{"corpusSize":2131,"step":161},{"corpusSize":2132,"step":162},{"corpusSize":2133,"step":163},{"corpusSize":2125,"step":164},{"corpusSize":2126,"step":165},{"corpusSize":2127,"step":166},{"corpusSize":2128,"step":167},{"corpusSize":2129,"step":168},{"corpusSize":2130,"step":169},{"corpusSize":2131,"step":170},{"corpusSize":2132,"step":171},{"corpusSize":2133,"step":172},{"corpusSize":2134,"step":173},{"corpusSize":2135,"step":174},{"corpusSize":2136,"step":175},{"corpusSize":2137,"step":176},{"corpusSize":2138,"step":177},{"corpusSize":2139,"step":178},{"corpusSize":2140,"step":179},{"corpusSize":2141,"step":180},{"corpusSize":2142,"step":181},{"corpusSize":2143,"step":182},{"corpusSize":2144,"step":183},{"corpusSize":2140,"step":184},{"corpusSize":2141,"step":185},{"corpusSize":2142,"step":186},{"corpusSize":2143,"step":187},{"corpusSize":2144,"step":188},{"corpusSize":2145,"step":189},{"corpusSize":2146,"step":190},{"corpusSize":2147,"step":191},{"corpusSize":2148,"step":192},{"corpusSize":2149,"step":193},{"corpusSize":2150,"step":194},{"corpusSize":2151,"step":195},{"corpusSize":2152,"step":196},{"corpusSize":2153,"step":197},{"corpusSize":2154,"step":198},{"corpusSize":2155,"step":199},{"corpusSize":2156,"step":200},{"corpusSize":2157,"step":201},{"corpusSize":2158,"step":202},{"corpusSize":2159,"step":203},{"corpusSize":2160,"step":204},{"corpusSize":2161,"step":205},{"corpusSize":2162,"step":206},{"corpusSize":2163,"step":207},{"corpusSize":2164,"step":208},{"corpusSize":2165,"step":209},{"corpusSize":2166,"step":210},{"corpusSize":2167,"step":211},{"corpusSize":2168,"step":212},{"corpusSize":2169,"step":213},{"corpusSize":2170,"step":214},{"corpusSize":2171,"step":215},{"corpusSize":2172,"step":216},{"corpusSize":2173,"step":217},{"corpusSize":2174,"step":218},{"corpusSize":2175,"step":219},{"corpusSize":2176,"step":220},{"corpusSize":2177,"step":221},{"corpusSize":2178,"step":222},{"corpusSize":2179,"step":223},{"corpusSize":2180,"step":224},{"corpusSize":2181,"step":225},{"corpusSize":2182,"step":226},{"corpusSize":2176,"step":227},{"corpusSize":2170,"step":228},{"corpusSize":2163,"step":229},{"corpusSize":2157,"step":230},{"corpusSize":2151,"step":231},{"corpusSize":2170,"step":232},{"corpusSize":2180,"step":233},{"corpusSize":2186,"step":234},{"corpusSize":2187,"step":235},{"corpusSize":2183,"step":236}]